{
  "name": {
    "git": "Test.js",
    "npm": "uupaa.test.js"
  },
  "build": {
    "files": [
      "lib/Test.js"
    ],
    "output": "release/Test.min.js",
    "target": [
      "Browser",
      "Worker",
      "Node"
    ]
  },
  "moduleTargets": {
    "uupaa.test.js": [
      "Browser",
      "Worker",
      "Node"
    ],
    "uupaa.task.js": [
      "Browser",
      "Worker",
      "Node"
    ],
    "uupaa.console.js": [
      "Worker"
    ],
    "uupaa.valid.js": [
      "Browser",
      "Worker",
      "Node"
    ],
    "uupaa.help.js": [
      "Browser"
    ],
    "uupaa.watch.js": [],
    "uupaa.plato.js": [],
    "uupaa.minify.js": []
  },
  "dependenciesFiles": [
    "node_modules/uupaa.task.js/lib/Task.js"
  ],
  "dependenciesModules": [
    "uupaa.task.js"
  ],
  "devDependenciesFiles": [
    "node_modules/uupaa.console.js/lib/Console.js",
    "node_modules/uupaa.valid.js/lib/Valid.js",
    "node_modules/uupaa.help.js/lib/Help.js",
    "node_modules/uupaa.watch.js/lib/Watch.js",
    "node_modules/uupaa.plato.js/lib/Plato.js",
    "node_modules/uupaa.minify.js/lib/Minify.js"
  ],
  "devDependenciesModules": [
    "uupaa.console.js",
    "uupaa.valid.js",
    "uupaa.help.js",
    "uupaa.watch.js",
    "uupaa.plato.js",
    "uupaa.minify.js"
  ]
}
